{"version":1,"resource":"file:///home/mustafaakil/tmp/ders/index.html","entries":[{"id":"pSHl.html","timestamp":1670851069168},{"id":"Zzdl.html","timestamp":1670851586668},{"id":"Dm42.html","timestamp":1670851662241},{"id":"RExv.html","timestamp":1670851690956},{"id":"p5Aw.html","timestamp":1670851705118},{"id":"uphP.html","timestamp":1670851717609},{"id":"jJtJ.html","timestamp":1670851738428},{"id":"j8yz.html","timestamp":1670851775710},{"id":"CAhO.html","timestamp":1670854683391},{"id":"fyu7.html","timestamp":1670854850479},{"id":"MKMJ.html","timestamp":1670854887550},{"id":"xrVY.html","timestamp":1670854976911},{"id":"IUoJ.html","timestamp":1670855020730},{"id":"Duy4.html","timestamp":1670855037733},{"id":"BBYt.html","timestamp":1670855147492},{"id":"TJ6N.html","timestamp":1670855165328},{"id":"Y2Is.html","timestamp":1670855329856},{"id":"IGCP.html","timestamp":1670855639829},{"id":"XVQ6.html","timestamp":1670855728308},{"id":"4OaR.html","timestamp":1670856200599},{"id":"syaa.html","timestamp":1670856262078},{"id":"Z7VK.html","timestamp":1670856276275},{"id":"eVJe.html","timestamp":1670856338408},{"id":"hKqN.html","timestamp":1670856386064},{"id":"vpnr.html","timestamp":1670856399140},{"id":"T1s0.html","timestamp":1670856409401},{"id":"y7Zv.html","timestamp":1670856456775},{"id":"Cf29.html","timestamp":1670856493034},{"id":"jkuZ.html","timestamp":1670857624052},{"id":"gIeG.html","timestamp":1670857636475},{"id":"1arz.html","timestamp":1670857661221},{"id":"AjF7.html","timestamp":1670857725405},{"id":"KG01.html","timestamp":1670857738961},{"id":"gI15.html","timestamp":1670857873011},{"id":"6vaP.html","timestamp":1670857933230},{"id":"HGsf.html","timestamp":1670858132394},{"id":"4Y0u.html","timestamp":1670858167567},{"id":"IRVD.html","timestamp":1670858287604},{"id":"uaUa.html","timestamp":1670858385522},{"id":"e3rJ.html","timestamp":1670858454808},{"id":"Iq2B.html","timestamp":1670858479696},{"id":"u2sC.html","timestamp":1670858574577},{"id":"KRep.html","timestamp":1670858598168},{"id":"3r85.html","timestamp":1670858616887},{"id":"KUfi.html","timestamp":1670858632447},{"id":"zMNC.html","timestamp":1670858860781}]}